caterpillar_pytest
